libdetectability/__init__.py
libdetectability/detectability.py
libdetectability/detectability_loss.py
libdetectability/segmented_detectability.py
libdetectability/test.py
libdetectability/experimental/__init__.py
libdetectability/experimental/detectability_loss_l1_det_tf.py
libdetectability/experimental/detectability_loss_l1_det_torch.py
libdetectability/internal/__init__.py
libdetectability/internal/centre_frequency.py
libdetectability/internal/erb_as_freq.py
libdetectability/internal/erbs_as_freq.py
libdetectability/internal/freq_as_erb.py
libdetectability/internal/freq_as_erbs.py
libdetectability/internal/gammatone_filterbank.py
libdetectability/internal/outer_middle_ear_filter.py
libdetectability/internal/threshold_in_quiet.py
libdetectability/internal/threshold_in_quiet_db.py
validation/__init__.py
validation/test_gammatone_filterbank.py
validation/test_outer_middle_ear_filter.py
validation/test_threshold_in_quiet.py
validation/test_threshold_in_quiet_db.py
libdetectability-0.8.1.dist-info/LICENSE
libdetectability-0.8.1.dist-info/METADATA
libdetectability-0.8.1.dist-info/WHEEL
libdetectability-0.8.1.dist-info/top_level.txt
libdetectability-0.8.1.dist-info/RECORD
