Metadata-Version: 2.1
Name: libdetectability
Version: 0.8.1
Summary: UNKNOWN
Home-page: UNKNOWN
License: UNKNOWN
Platform: UNKNOWN
License-File: LICENSE
Requires-Dist: pytest
Requires-Dist: numpy
Requires-Dist: scipy
Requires-Dist: torch
Requires-Dist: libsegmenter
